hf_hub_prompts/__init__.py
hf_hub_prompts/constants.py
hf_hub_prompts/hub_api.py
hf_hub_prompts/populated_prompt.py
hf_hub_prompts/prompt_templates.py
hf_hub_prompts/tools.py
hf_hub_prompts-0.0.7.dist-info/LICENSE.txt
hf_hub_prompts-0.0.7.dist-info/METADATA
hf_hub_prompts-0.0.7.dist-info/WHEEL
hf_hub_prompts-0.0.7.dist-info/RECORD
