Metadata-Version: 2.1
Name: hf-hub-prompts
Version: 0.0.7
Summary: An experimental library for working with prompts on the Hugging Face Hub.
Home-page: https://github.com/MoritzLaurer/hf_hub_prompts
License: Appache-2.0
Author: MoritzLaurer
Author-email: moritz@huggingface.co
Requires-Python: >=3.10,<4.0
Classifier: License :: Other/Proprietary License
Classifier: Programming Language :: Python :: 3
Classifier: Programming Language :: Python :: 3.10
Classifier: Programming Language :: Python :: 3.11
Classifier: Programming Language :: Python :: 3.12
Classifier: Programming Language :: Python :: 3.13
Provides-Extra: inference
Requires-Dist: accelerate (>=1.0.1,<2.0.0) ; extra == "inference"
Requires-Dist: anthropic (>=0.36.0,<0.37.0) ; extra == "inference"
Requires-Dist: boto3 (>=1.35.39,<2.0.0) ; extra == "inference"
Requires-Dist: datasets (>=2.21.0,<3.0.0)
Requires-Dist: huggingface-hub (>=0.25.2,<0.26.0)
Requires-Dist: langchain-anthropic (>=0.2.3,<0.3.0) ; extra == "inference"
Requires-Dist: langchain-core (>=0.3.12,<0.4.0) ; extra == "inference"
Requires-Dist: langchain-openai (>=0.2.2,<0.3.0) ; extra == "inference"
Requires-Dist: langchainhub (>=0.1.21,<0.2.0) ; extra == "inference"
Requires-Dist: langgraph (>=0.2.38,<0.3.0) ; extra == "inference"
Requires-Dist: numpy (>=1.26.0,<2.0.0)
Requires-Dist: openai (>=1.51.0,<2.0.0) ; extra == "inference"
Requires-Dist: python-dotenv (>=1.0.1,<2.0.0)
Requires-Dist: transformers (>=4.45.2,<5.0.0) ; extra == "inference"
Requires-Dist: yfinance (>=0.2.50,<0.3.0) ; extra == "inference"
